setup.py
txconnpool/__init__.py
txconnpool/pool.py
txconnpool.egg-info/PKG-INFO
txconnpool.egg-info/SOURCES.txt
txconnpool.egg-info/dependency_links.txt
txconnpool.egg-info/not-zip-safe
txconnpool.egg-info/top_level.txt
txconnpool/test/__init__.py
txconnpool/test/test_basic.py