Metadata-Version: 1.0
Name: txconnpool
Version: 0.1.1
Summary: A generalized connection pooling library for Twisted
Home-page: http://github.com/ericflo/txconnpool/
Author: Eric Florenzano
Author-email: floguy@gmail.com
License: Apache
Keywords: twisted,connection,pool,connpool,txconnpool
Platform: UNKNOWN
Classifier: Programming Language :: Python
Classifier: Topic :: Software Development :: Libraries :: Python Modules
Classifier: Framework :: Twisted
Classifier: Environment :: Web Environment
